CHANGELOG.md
README.md
tartufo/__init__.py
tartufo/__main__.py
tartufo/cli.py
tartufo/commands/__init__.py
tartufo/commands/pre_commit.py
tartufo/commands/scan_folder.py
tartufo/commands/scan_local_repo.py
tartufo/commands/scan_remote_repo.py
tartufo/commands/update_signatures.py
tartufo/config.py
tartufo/data/default_regexes.json
tartufo/py.typed
tartufo/scanner.py
tartufo/types.py
tartufo/util.py
tartufo-5.0.2.dist-info/LICENSE
tartufo-5.0.2.dist-info/METADATA
tartufo-5.0.2.dist-info/WHEEL
tartufo-5.0.2.dist-info/entry_points.txt
tartufo-5.0.2.dist-info/RECORD
