Metadata-Version: 2.1
Name: tartufo
Version: 5.0.2
Summary: tartufo is a tool for scanning git repositories for secrets/passwords/high-entropy data
Home-page: https://github.com/godaddy/tartufo/
License: GPL-2.0-only
Keywords: git,security,secrets,entropy,scanner
Author: GoDaddy
Author-email: oss@godaddy.com
Maintainer: GoDaddy
Maintainer-email: oss@godaddy.com
Requires-Python: >=3.8,<3.14
Classifier: Development Status :: 5 - Production/Stable
Classifier: Environment :: Console
Classifier: Intended Audience :: Developers
Classifier: License :: OSI Approved :: GNU General Public License v2 (GPLv2)
Classifier: Natural Language :: English
Classifier: Operating System :: OS Independent
Classifier: Programming Language :: Python
Classifier: Programming Language :: Python :: 3
Classifier: Programming Language :: Python :: 3.8
Classifier: Programming Language :: Python :: 3.9
Classifier: Programming Language :: Python :: 3.10
Classifier: Programming Language :: Python :: 3.11
Classifier: Programming Language :: Python :: 3.12
Classifier: Programming Language :: Python :: 3.13
Classifier: Programming Language :: Python :: Implementation :: CPython
Classifier: Programming Language :: Python :: Implementation :: PyPy
Classifier: Topic :: Security
Classifier: Topic :: Software Development :: Version Control :: Git
Classifier: Typing :: Typed
Requires-Dist: GitPython (>=3.1.43,<4.0.0)
Requires-Dist: cached-property (>=1.5.2,<2.0.0)
Requires-Dist: click (>=8.1.7,<9.0.0)
Requires-Dist: colorama ; sys_platform == "win32"
Requires-Dist: pygit2 (>=1.11.0,<2.0.0) ; python_version < "3.10"
Requires-Dist: pygit2 (>=1.16.0,<2.0.0) ; python_version >= "3.10"
Requires-Dist: tomlkit (>=0.13.0,<0.14.0)
Project-URL: Documentation, https://tartufo.readthedocs.io/
Project-URL: Repository, https://github.com/godaddy/tartufo/
